{
  "Logging": {
    "LogLevel": {
      "Default": "Information",
      "Microsoft.AspNetCore": "Warning"
    }
  },
  "AllowedHosts": "*",
  "ConnectionStrings": {
    "LocalDbFile": "Replace with your connectionstring"
  },
  "Authentication": {
    "Google": {
      "ClientId": "Replace with your ClientId",
      "ClientSecret": "Replace with your ClientSecret"
    },
    "GitHub": {
      "ClientId": "Replace with your ClientId",
      "ClientSecret": "Replace with your ClientSecret"
    }
  }
}